[{"restrictions": [], "description": "Double-click to apply to a piece of armor.", "name": "Superior Rune of the Mad King", "level": 60, "type": "UpgradeComponent", "rarity": "Exotic", "vendor_value": 65, "details": {"infix_upgrade": {"attributes": []}, "suffix": "of the Mad King", "infusion_upgrade_flags": [], "bonuses": ["+25 Power", "+5% Condition Duration", "+50 Power", "+15% Bleeding Duration", "+100 Power", "+20% bleeding duration; summon ravens to attack nearby enemies when you activate an elite skill. <c=@reminder>(Cooldown: 45 Seconds)</c>"], "flags": ["HeavyArmor", "LightArmor", "MediumArmor"], "type": "Rune"}, "game_types": ["Activity", "Wvw", "Dungeon", "Pve"], "flags": [], "chat_link": "[&AgHMjAAA]", "id": 36044, "icon": "https://render.guildwars2.com/file/0A0E6F80DA16D7764FFEA33893B66051FBE07A3F/499379.png"}, {"restrictions": [], "name": "Mad King's Coat", "level": 80, "type": "Armor", "default_skin": 8, "rarity": "Exotic", "vendor_value": 396, "details": {"infusion_slots": [], "infix_upgrade": {"attributes": [{"attribute": "ConditionDamage", "modifier": 134}, {"attribute": "Toughness", "modifier": 96}, {"attribute": "Vitality", "modifier": 96}]}, "suffix_item_id": 36044, "secondary_suffix_item_id": "", "weight_class": "Heavy", "defense": 363, "type": "Coat"}, "game_types": ["Activity", "Wvw", "Dungeon", "Pve"], "flags": ["HideSuffix", "AccountBound", "NoSell", "AccountBindOnUse"], "chat_link": "[&AgGBLQEA]", "id": 77185, "icon": "https://render.guildwars2.com/file/B6B564EFEBF6A3075A27E96F1DB97779139EA0D2/61044.png"}, {"restrictions": [], "name": "Gauntlets of Madness", "level": 80, "type": "Armor", "default_skin": 929, "rarity": "Exotic", "vendor_value": 238, "details": {"infusion_slots": [], "suffix_item_id": 36044, "secondary_suffix_item_id": "", "weight_class": "Heavy", "defense": 182, "type": "Gloves"}, "game_types": ["Activity", "Wvw", "Dungeon", "Pve"], "flags": ["HideSuffix", "AccountBound", "NoSalvage", "NoSell", "SoulBindOnUse"], "chat_link": "[&AgGqvgAA]", "id": 48810, "icon": "https://render.guildwars2.com/file/0B32EF80050D29BDA30B0ABD04010B9CF5CC2403/61270.png"}, {"restrictions": [], "description": "", "name": "Mad King's Slippers", "level": 80, "type": "Armor", "default_skin": 35, "rarity": "Exotic", "vendor_value": 264, "details": {"infusion_slots": [], "suffix_item_id": 36044, "secondary_suffix_item_id": "", "weight_class": "Medium", "defense": 157, "type": "Boots"}, "game_types": ["Activity", "Wvw", "Dungeon", "Pve"], "flags": ["HideSuffix", "NoSalvage", "SoulbindOnAcquire", "SoulBindOnUse"], "chat_link": "[&AgGsjAAA]", "id": 36012, "icon": "https://render.guildwars2.com/file/B7D77D6B1735D07F4AB93DE2DED06A1FEBB7F3EE/561550.png"}, {"restrictions": [], "description": "", "name": "Mad King's Slippers", "level": 80, "type": "Armor", "default_skin": 30, "rarity": "Exotic", "vendor_value": 264, "details": {"infusion_slots": [], "suffix_item_id": 36044, "secondary_suffix_item_id": "", "weight_class": "Light", "defense": 133, "type": "Boots"}, "game_types": ["Activity", "Wvw", "Dungeon", "Pve"], "flags": ["HideSuffix", "NoSalvage", "SoulbindOnAcquire", "SoulBindOnUse"], "chat_link": "[&AgGrjAAA]", "id": 36011, "icon": "https://render.guildwars2.com/file/F640924D5B38FAFAF55BDF9496D41266A132A83C/61027.png"}, {"restrictions": [], "description": "", "name": "Mad King's Slippers", "level": 80, "type": "Armor", "default_skin": 27, "rarity": "Exotic", "vendor_value": 264, "details": {"infusion_slots": [], "suffix_item_id": 36044, "secondary_suffix_item_id": "", "weight_class": "Heavy", "defense": 182, "type": "Boots"}, "game_types": ["Activity", "Wvw", "Dungeon", "Pve"], "flags": ["HideSuffix", "NoSalvage", "SoulbindOnAcquire", "SoulBindOnUse"], "chat_link": "[&AgGqjAAA]", "id": 36010, "icon": "https://render.guildwars2.com/file/B1C7DC687A5492E42AF06680931D7635DB022C91/61037.png"}, {"restrictions": [], "name": "Mad King's Overcoat", "level": 80, "type": "Armor", "default_skin": 12, "rarity": "Exotic", "vendor_value": 396, "details": {"infusion_slots": [], "infix_upgrade": {"attributes": [{"attribute": "ConditionDamage", "modifier": 134}, {"attribute": "Toughness", "modifier": 96}, {"attribute": "Vitality", "modifier": 96}]}, "suffix_item_id": 36044, "secondary_suffix_item_id": "", "weight_class": "Medium", "defense": 338, "type": "Coat"}, "game_types": ["Activity", "Wvw", "Dungeon", "Pve"], "flags": ["HideSuffix", "AccountBound", "NoSell", "AccountBindOnUse"], "chat_link": "[&AgE8KwEA]", "id": 76604, "icon": "https://render.guildwars2.com/file/142DBA7E1144E3A61A02D9C8EC44225F327597F2/561549.png"}, {"restrictions": [], "name": "Mad King's Vestment", "level": 80, "type": "Armor", "default_skin": 9, "rarity": "Exotic", "vendor_value": 396, "details": {"infusion_slots": [], "infix_upgrade": {"attributes": [{"attribute": "ConditionDamage", "modifier": 134}, {"attribute": "Toughness", "modifier": 96}, {"attribute": "Vitality", "modifier": 96}]}, "suffix_item_id": 36044, "secondary_suffix_item_id": "", "weight_class": "Light", "defense": 314, "type": "Coat"}, "game_types": ["Activity", "Wvw", "Dungeon", "Pve"], "flags": ["HideSuffix", "AccountBound", "NoSell", "AccountBindOnUse"], "chat_link": "[&AgFiHgEA]", "id": 73314, "icon": "https://render.guildwars2.com/file/FB0AA64F98303AE5112408EF3DC8C7307EA118F8/61011.png"}, {"restrictions": [], "name": "Armwraps of Madness", "level": 80, "type": "Armor", "default_skin": 930, "rarity": "Exotic", "vendor_value": 238, "details": {"infusion_slots": [], "suffix_item_id": 36044, "secondary_suffix_item_id": "", "weight_class": "Light", "defense": 133, "type": "Gloves"}, "game_types": ["Activity", "Wvw", "Dungeon", "Pve"], "flags": ["HideSuffix", "AccountBound", "NoSalvage", "NoSell", "SoulBindOnUse"], "chat_link": "[&AgGpvgAA]", "id": 48809, "icon": "https://render.guildwars2.com/file/170340BAA20B7CF9BEB99D10DEC79B0F4499BC21/61275.png"}, {"restrictions": [], "name": "Gloves of Madness", "level": 80, "type": "Armor", "default_skin": 935, "rarity": "Exotic", "vendor_value": 238, "details": {"infusion_slots": [], "suffix_item_id": 36044, "secondary_suffix_item_id": "", "weight_class": "Medium", "defense": 157, "type": "Gloves"}, "game_types": ["Activity", "Wvw", "Dungeon", "Pve"], "flags": ["HideSuffix", "AccountBound", "NoSalvage", "NoSell", "SoulBindOnUse"], "chat_link": "[&AgGovgAA]", "id": 48808, "icon": "https://render.guildwars2.com/file/92C9AD5F330111974B3E3D08052510B8BE08FF9C/61280.png"}, {"restrictions": [], "description": "", "name": "Mad King's Overcoat", "level": 80, "type": "Armor", "default_skin": 9, "rarity": "Exotic", "vendor_value": 396, "details": {"infusion_slots": [], "suffix_item_id": 36044, "secondary_suffix_item_id": "", "weight_class": "Light", "defense": 314, "type": "Coat"}, "game_types": ["Activity", "Wvw", "Dungeon", "Pve"], "flags": ["HideSuffix", "AccountBound", "SoulBindOnUse"], "chat_link": "[&AgGfjAAA]", "id": 35999, "icon": "https://render.guildwars2.com/file/FB0AA64F98303AE5112408EF3DC8C7307EA118F8/61011.png"}, {"restrictions": [], "description": "", "name": "Mad King's Slippers", "level": 80, "type": "Armor", "default_skin": 30, "rarity": "Exotic", "vendor_value": 264, "details": {"infusion_slots": [], "suffix_item_id": 36044, "secondary_suffix_item_id": "", "weight_class": "Light", "defense": 133, "type": "Boots"}, "game_types": ["Activity", "Wvw", "Dungeon", "Pve"], "flags": ["HideSuffix", "AccountBound", "SoulBindOnUse"], "chat_link": "[&AgGejAAA]", "id": 35998, "icon": "https://render.guildwars2.com/file/F640924D5B38FAFAF55BDF9496D41266A132A83C/61027.png"}, {"restrictions": [], "description": "", "name": "Mad King's Shoulders", "level": 80, "type": "Armor", "default_skin": 38, "rarity": "Exotic", "vendor_value": 291, "details": {"infusion_slots": [], "suffix_item_id": 36044, "secondary_suffix_item_id": "", "weight_class": "Heavy", "defense": 121, "type": "Shoulders"}, "game_types": ["Activity", "Wvw", "Dungeon", "Pve"], "flags": ["HideSuffix", "AccountBound", "SoulBindOnUse"], "chat_link": "[&AgGdjAAA]", "id": 35997, "icon": "https://render.guildwars2.com/file/14A85D487B6B77CF13F86D00D55205B3F25E9F32/61076.png"}, {"restrictions": [], "description": "", "name": "Mad King's Britches", "level": 80, "type": "Armor", "default_skin": 7, "rarity": "Exotic", "vendor_value": 370, "details": {"infusion_slots": [], "suffix_item_id": 36044, "secondary_suffix_item_id": "", "weight_class": "Heavy", "defense": 242, "type": "Leggings"}, "game_types": ["Activity", "Wvw", "Dungeon", "Pve"], "flags": ["HideSuffix", "AccountBound", "SoulBindOnUse"], "chat_link": "[&AgGcjAAA]", "id": 35996, "icon": "https://render.guildwars2.com/file/2AD0FE1D59CBE7ED40FABF3E9F5E26DA22930E19/61068.png"}, {"restrictions": [], "description": "", "name": "Mad King's Crown", "level": 80, "type": "Armor", "default_skin": 92, "rarity": "Exotic", "vendor_value": 330, "details": {"infusion_slots": [], "suffix_item_id": 36044, "secondary_suffix_item_id": "", "weight_class": "Heavy", "defense": 121, "type": "Helm"}, "game_types": ["Activity", "Wvw", "Dungeon", "Pve"], "flags": ["HideSuffix", "AccountBound", "SoulBindOnUse"], "chat_link": "[&AgGbjAAA]", "id": 35995, "icon": "https://render.guildwars2.com/file/021990D72EDC97286192C33973D3A74D4D466BB6/61061.png"}, {"restrictions": [], "description": "", "name": "Mad King's Mittens", "level": 80, "type": "Armor", "default_skin": 33, "rarity": "Exotic", "vendor_value": 238, "details": {"infusion_slots": [], "suffix_item_id": 36044, "secondary_suffix_item_id": "", "weight_class": "Heavy", "defense": 182, "type": "Gloves"}, "game_types": ["Activity", "Wvw", "Dungeon", "Pve"], "flags": ["HideSuffix", "AccountBound", "SoulBindOnUse"], "chat_link": "[&AgGajAAA]", "id": 35994, "icon": "https://render.guildwars2.com/file/71F39428A82C6AE7C79C6620066E0C6947FF5D72/61054.png"}, {"restrictions": [], "description": "", "name": "Mad King's Overcoat", "level": 80, "type": "Armor", "default_skin": 8, "rarity": "Exotic", "vendor_value": 396, "details": {"infusion_slots": [], "suffix_item_id": 36044, "secondary_suffix_item_id": "", "weight_class": "Heavy", "defense": 363, "type": "Coat"}, "game_types": ["Activity", "Wvw", "Dungeon", "Pve"], "flags": ["HideSuffix", "AccountBound", "SoulBindOnUse"], "chat_link": "[&AgGZjAAA]", "id": 35993, "icon": "https://render.guildwars2.com/file/B6B564EFEBF6A3075A27E96F1DB97779139EA0D2/61044.png"}, {"restrictions": [], "description": "", "name": "Mad King's Slippers", "level": 80, "type": "Armor", "default_skin": 27, "rarity": "Exotic", "vendor_value": 264, "details": {"infusion_slots": [], "suffix_item_id": 36044, "secondary_suffix_item_id": "", "weight_class": "Heavy", "defense": 182, "type": "Boots"}, "game_types": ["Activity", "Wvw", "Dungeon", "Pve"], "flags": ["HideSuffix", "AccountBound", "SoulBindOnUse"], "chat_link": "[&AgGYjAAA]", "id": 35992, "icon": "https://render.guildwars2.com/file/B1C7DC687A5492E42AF06680931D7635DB022C91/61037.png"}, {"restrictions": [], "description": "", "name": "Mad King's Mittens", "level": 80, "type": "Armor", "default_skin": 39, "rarity": "Exotic", "vendor_value": 238, "details": {"infusion_slots": [], "suffix_item_id": 36044, "secondary_suffix_item_id": "", "weight_class": "Light", "defense": 133, "type": "Gloves"}, "game_types": ["Activity", "Wvw", "Dungeon", "Pve"], "flags": ["HideSuffix", "AccountBound", "SoulBindOnUse"], "chat_link": "[&AgGgjAAA]", "id": 36000, "icon": "https://render.guildwars2.com/file/DBE75334171A7FF19A6DA42F0C0355913505B92D/61073.png"}, {"restrictions": [], "description": "", "name": "Mad King's Crown", "level": 80, "type": "Armor", "default_skin": 94, "rarity": "Exotic", "vendor_value": 330, "details": {"infusion_slots": [], "suffix_item_id": 36044, "secondary_suffix_item_id": "", "weight_class": "Light", "defense": 73, "type": "Helm"}, "game_types": ["Activity", "Wvw", "Dungeon", "Pve"], "flags": ["HideSuffix", "AccountBound", "SoulBindOnUse"], "chat_link": "[&AgGhjAAA]", "id": 36001, "icon": "https://render.guildwars2.com/file/3F43DAA7D2171B41B6F216804AC321E0B1B9A3AA/61083.png"}, {"restrictions": [], "description": "", "name": "Mad King's Britches", "level": 80, "type": "Armor", "default_skin": 10, "rarity": "Exotic", "vendor_value": 370, "details": {"infusion_slots": [], "suffix_item_id": 36044, "secondary_suffix_item_id": "", "weight_class": "Light", "defense": 194, "type": "Leggings"}, "game_types": ["Activity", "Wvw", "Dungeon", "Pve"], "flags": ["HideSuffix", "AccountBound", "SoulBindOnUse"], "chat_link": "[&AgGijAAA]", "id": 36002, "icon": "https://render.guildwars2.com/file/1920ACA302E656B60C38605521760351F147809D/61088.png"}, {"restrictions": [], "description": "", "name": "Mad King's Shoulders", "level": 80, "type": "Armor", "default_skin": 45, "rarity": "Exotic", "vendor_value": 291, "details": {"infusion_slots": [], "suffix_item_id": 36044, "secondary_suffix_item_id": "", "weight_class": "Light", "defense": 73, "type": "Shoulders"}, "game_types": ["Activity", "Wvw", "Dungeon", "Pve"], "flags": ["HideSuffix", "AccountBound", "SoulBindOnUse"], "chat_link": "[&AgGjjAAA]", "id": 36003, "icon": "https://render.guildwars2.com/file/0F6E6E6F4D0802BD4FBB9425BDBDD476B704D9C8/61092.png"}, {"restrictions": [], "description": "", "name": "Mad King's Slippers", "level": 80, "type": "Armor", "default_skin": 35, "rarity": "Exotic", "vendor_value": 264, "details": {"infusion_slots": [], "suffix_item_id": 36044, "secondary_suffix_item_id": "", "weight_class": "Medium", "defense": 157, "type": "Boots"}, "game_types": ["Activity", "Wvw", "Dungeon", "Pve"], "flags": ["HideSuffix", "AccountBound", "SoulBindOnUse"], "chat_link": "[&AgGkjAAA]", "id": 36004, "icon": "https://render.guildwars2.com/file/B7D77D6B1735D07F4AB93DE2DED06A1FEBB7F3EE/561550.png"}, {"restrictions": [], "description": "", "name": "Mad King's Overcoat", "level": 80, "type": "Armor", "default_skin": 12, "rarity": "Exotic", "vendor_value": 396, "details": {"infusion_slots": [], "suffix_item_id": 36044, "secondary_suffix_item_id": "", "weight_class": "Medium", "defense": 338, "type": "Coat"}, "game_types": ["Activity", "Wvw", "Dungeon", "Pve"], "flags": ["HideSuffix", "AccountBound", "SoulBindOnUse"], "chat_link": "[&AgGljAAA]", "id": 36005, "icon": "https://render.guildwars2.com/file/142DBA7E1144E3A61A02D9C8EC44225F327597F2/561549.png"}, {"restrictions": [], "description": "", "name": "Mad King's Mittens", "level": 80, "type": "Armor", "default_skin": 43, "rarity": "Exotic", "vendor_value": 238, "details": {"infusion_slots": [], "suffix_item_id": 36044, "secondary_suffix_item_id": "", "weight_class": "Medium", "defense": 157, "type": "Gloves"}, "game_types": ["Activity", "Wvw", "Dungeon", "Pve"], "flags": ["HideSuffix", "AccountBound", "SoulBindOnUse"], "chat_link": "[&AgGmjAAA]", "id": 36006, "icon": "https://render.guildwars2.com/file/3F385C09CDDF9F5509E4C79F66B1733F186D3D6F/561552.png"}, {"restrictions": [], "description": "", "name": "Mad King's Crown", "level": 80, "type": "Armor", "default_skin": 95, "rarity": "Exotic", "vendor_value": 330, "details": {"infusion_slots": [], "suffix_item_id": 36044, "secondary_suffix_item_id": "", "weight_class": "Medium", "defense": 97, "type": "Helm"}, "game_types": ["Activity", "Wvw", "Dungeon", "Pve"], "flags": ["HideSuffix", "AccountBound", "SoulBindOnUse"], "chat_link": "[&AgGnjAAA]", "id": 36007, "icon": "https://render.guildwars2.com/file/65A0C7367206E6CE4EC7C8CBE07EABAE0191BFBA/561548.png"}, {"restrictions": [], "description": "", "name": "Mad King's Britches", "level": 80, "type": "Armor", "default_skin": 11, "rarity": "Exotic", "vendor_value": 370, "details": {"infusion_slots": [], "suffix_item_id": 36044, "secondary_suffix_item_id": "", "weight_class": "Medium", "defense": 218, "type": "Leggings"}, "game_types": ["Activity", "Wvw", "Dungeon", "Pve"], "flags": ["HideSuffix", "AccountBound", "SoulBindOnUse"], "chat_link": "[&AgGojAAA]", "id": 36008, "icon": "https://render.guildwars2.com/file/DD4D5CEC01DD45E656A7B6DA540161385D78B2B8/561553.png"}, {"restrictions": [], "description": "", "name": "Mad King's Shoulders", "level": 80, "type": "Armor", "default_skin": 47, "rarity": "Exotic", "vendor_value": 291, "details": {"infusion_slots": [], "suffix_item_id": 36044, "secondary_suffix_item_id": "", "weight_class": "Medium", "defense": 97, "type": "Shoulders"}, "game_types": ["Activity", "Wvw", "Dungeon", "Pve"], "flags": ["HideSuffix", "AccountBound", "SoulBindOnUse"], "chat_link": "[&AgGpjAAA]", "id": 36009, "icon": "https://render.guildwars2.com/file/EF97346C5442020AFAAAF016182F0CF00E989703/561551.png"}]